[{"model": "sat.estado", "pk": 1, "fields": {"clave": "AGU", "pais": "MEX", "descripcion": "Aguascalientes"}}, {"model": "sat.estado", "pk": 2, "fields": {"clave": "BCN", "pais": "MEX", "descripcion": "Baja California"}}, {"model": "sat.estado", "pk": 3, "fields": {"clave": "BCS", "pais": "MEX", "descripcion": "Baja California Sur"}}, {"model": "sat.estado", "pk": 4, "fields": {"clave": "CAM", "pais": "MEX", "descripcion": "Campeche"}}, {"model": "sat.estado", "pk": 5, "fields": {"clave": "CHP", "pais": "MEX", "descripcion": "Chiapas"}}, {"model": "sat.estado", "pk": 6, "fields": {"clave": "CHH", "pais": "MEX", "descripcion": "Chihuahua"}}, {"model": "sat.estado", "pk": 7, "fields": {"clave": "COA", "pais": "MEX", "descripcion": "Coahuila"}}, {"model": "sat.estado", "pk": 8, "fields": {"clave": "COL", "pais": "MEX", "descripcion": "Colima"}}, {"model": "sat.estado", "pk": 9, "fields": {"clave": "DIF", "pais": "MEX", "descripcion": "Ciudad de M\u00e9xico"}}, {"model": "sat.estado", "pk": 10, "fields": {"clave": "DUR", "pais": "MEX", "descripcion": "Durango"}}, {"model": "sat.estado", "pk": 11, "fields": {"clave": "GUA", "pais": "MEX", "descripcion": "Guanajuato"}}, {"model": "sat.estado", "pk": 12, "fields": {"clave": "GRO", "pais": "MEX", "descripcion": "Guerrero"}}, {"model": "sat.estado", "pk": 13, "fields": {"clave": "HID", "pais": "MEX", "descripcion": "Hidalgo"}}, {"model": "sat.estado", "pk": 14, "fields": {"clave": "JAL", "pais": "MEX", "descripcion": "Jalisco"}}, {"model": "sat.estado", "pk": 15, "fields": {"clave": "MEX", "pais": "MEX", "descripcion": "Estado de M\u00e9xico"}}, {"model": "sat.estado", "pk": 16, "fields": {"clave": "MIC", "pais": "MEX", "descripcion": "Michoac\u00e1n"}}, {"model": "sat.estado", "pk": 17, "fields": {"clave": "MOR", "pais": "MEX", "descripcion": "Morelos"}}, {"model": "sat.estado", "pk": 18, "fields": {"clave": "NAY", "pais": "MEX", "descripcion": "Nayarit"}}, {"model": "sat.estado", "pk": 19, "fields": {"clave": "NLE", "pais": "MEX", "descripcion": "Nuevo Le\u00f3n"}}, {"model": "sat.estado", "pk": 20, "fields": {"clave": "OAX", "pais": "MEX", "descripcion": "Oaxaca"}}, {"model": "sat.estado", "pk": 21, "fields": {"clave": "PUE", "pais": "MEX", "descripcion": "Puebla"}}, {"model": "sat.estado", "pk": 22, "fields": {"clave": "QUE", "pais": "MEX", "descripcion": "Quer\u00e9taro"}}, {"model": "sat.estado", "pk": 23, "fields": {"clave": "ROO", "pais": "MEX", "descripcion": "Quintana Roo"}}, {"model": "sat.estado", "pk": 24, "fields": {"clave": "SLP", "pais": "MEX", "descripcion": "San Luis Potos\u00ed"}}, {"model": "sat.estado", "pk": 25, "fields": {"clave": "SIN", "pais": "MEX", "descripcion": "Sinaloa"}}, {"model": "sat.estado", "pk": 26, "fields": {"clave": "SON", "pais": "MEX", "descripcion": "Sonora"}}, {"model": "sat.estado", "pk": 27, "fields": {"clave": "TAB", "pais": "MEX", "descripcion": "Tabasco"}}, {"model": "sat.estado", "pk": 28, "fields": {"clave": "TAM", "pais": "MEX", "descripcion": "Tamaulipas"}}, {"model": "sat.estado", "pk": 29, "fields": {"clave": "TLA", "pais": "MEX", "descripcion": "Tlaxcala"}}, {"model": "sat.estado", "pk": 30, "fields": {"clave": "VER", "pais": "MEX", "descripcion": "Veracruz"}}, {"model": "sat.estado", "pk": 31, "fields": {"clave": "YUC", "pais": "MEX", "descripcion": "Yucat\u00e1n"}}, {"model": "sat.estado", "pk": 32, "fields": {"clave": "ZAC", "pais": "MEX", "descripcion": "Zacatecas"}}, {"model": "sat.estado", "pk": 33, "fields": {"clave": "AL", "pais": "USA", "descripcion": "Alabama"}}, {"model": "sat.estado", "pk": 34, "fields": {"clave": "AK", "pais": "USA", "descripcion": "Alaska"}}, {"model": "sat.estado", "pk": 35, "fields": {"clave": "AZ", "pais": "USA", "descripcion": "Arizona"}}, {"model": "sat.estado", "pk": 36, "fields": {"clave": "AR", "pais": "USA", "descripcion": "Arkansas"}}, {"model": "sat.estado", "pk": 37, "fields": {"clave": "CA", "pais": "USA", "descripcion": "California"}}, {"model": "sat.estado", "pk": 38, "fields": {"clave": "NC", "pais": "USA", "descripcion": "Carolina del Norte"}}, {"model": "sat.estado", "pk": 39, "fields": {"clave": "SC", "pais": "USA", "descripcion": "Carolina del Sur"}}, {"model": "sat.estado", "pk": 40, "fields": {"clave": "CO", "pais": "USA", "descripcion": "Colorado"}}, {"model": "sat.estado", "pk": 41, "fields": {"clave": "CT", "pais": "USA", "descripcion": "Connecticut"}}, {"model": "sat.estado", "pk": 42, "fields": {"clave": "ND", "pais": "USA", "descripcion": "Dakota del Norte"}}, {"model": "sat.estado", "pk": 43, "fields": {"clave": "SD", "pais": "USA", "descripcion": "Dakota del Sur"}}, {"model": "sat.estado", "pk": 44, "fields": {"clave": "DE", "pais": "USA", "descripcion": "Delaware"}}, {"model": "sat.estado", "pk": 45, "fields": {"clave": "FL", "pais": "USA", "descripcion": "Florida"}}, {"model": "sat.estado", "pk": 46, "fields": {"clave": "GA", "pais": "USA", "descripcion": "Georgia"}}, {"model": "sat.estado", "pk": 47, "fields": {"clave": "HI", "pais": "USA", "descripcion": "Haw\u00e1i"}}, {"model": "sat.estado", "pk": 48, "fields": {"clave": "ID", "pais": "USA", "descripcion": "Idaho"}}, {"model": "sat.estado", "pk": 49, "fields": {"clave": "IL", "pais": "USA", "descripcion": "Illinois"}}, {"model": "sat.estado", "pk": 50, "fields": {"clave": "IN", "pais": "USA", "descripcion": "Indiana"}}, {"model": "sat.estado", "pk": 51, "fields": {"clave": "IA", "pais": "USA", "descripcion": "Iowa"}}, {"model": "sat.estado", "pk": 52, "fields": {"clave": "KS", "pais": "USA", "descripcion": "Kansas"}}, {"model": "sat.estado", "pk": 53, "fields": {"clave": "KY", "pais": "USA", "descripcion": "Kentucky"}}, {"model": "sat.estado", "pk": 54, "fields": {"clave": "LA", "pais": "USA", "descripcion": "Luisiana"}}, {"model": "sat.estado", "pk": 55, "fields": {"clave": "ME", "pais": "USA", "descripcion": "Maine"}}, {"model": "sat.estado", "pk": 56, "fields": {"clave": "MD", "pais": "USA", "descripcion": "Maryland"}}, {"model": "sat.estado", "pk": 57, "fields": {"clave": "MA", "pais": "USA", "descripcion": "Massachusetts"}}, {"model": "sat.estado", "pk": 58, "fields": {"clave": "MI", "pais": "USA", "descripcion": "M\u00edchigan"}}, {"model": "sat.estado", "pk": 59, "fields": {"clave": "MN", "pais": "USA", "descripcion": "Minnesota"}}, {"model": "sat.estado", "pk": 60, "fields": {"clave": "MS", "pais": "USA", "descripcion": "Misisipi"}}, {"model": "sat.estado", "pk": 61, "fields": {"clave": "MO", "pais": "USA", "descripcion": "Misuri"}}, {"model": "sat.estado", "pk": 62, "fields": {"clave": "MT", "pais": "USA", "descripcion": "Montana"}}, {"model": "sat.estado", "pk": 63, "fields": {"clave": "NE", "pais": "USA", "descripcion": "Nebraska"}}, {"model": "sat.estado", "pk": 64, "fields": {"clave": "NV", "pais": "USA", "descripcion": "Nevada"}}, {"model": "sat.estado", "pk": 65, "fields": {"clave": "NJ", "pais": "USA", "descripcion": "Nueva Jersey"}}, {"model": "sat.estado", "pk": 66, "fields": {"clave": "NY", "pais": "USA", "descripcion": "Nueva York"}}, {"model": "sat.estado", "pk": 67, "fields": {"clave": "NH", "pais": "USA", "descripcion": "Nuevo Hampshire"}}, {"model": "sat.estado", "pk": 68, "fields": {"clave": "NM", "pais": "USA", "descripcion": "Nuevo M\u00e9xico"}}, {"model": "sat.estado", "pk": 69, "fields": {"clave": "OH", "pais": "USA", "descripcion": "Ohio"}}, {"model": "sat.estado", "pk": 70, "fields": {"clave": "OK", "pais": "USA", "descripcion": "Oklahoma"}}, {"model": "sat.estado", "pk": 71, "fields": {"clave": "OR", "pais": "USA", "descripcion": "Oreg\u00f3n"}}, {"model": "sat.estado", "pk": 72, "fields": {"clave": "PA", "pais": "USA", "descripcion": "Pensilvania"}}, {"model": "sat.estado", "pk": 73, "fields": {"clave": "RI", "pais": "USA", "descripcion": "Rhode Island"}}, {"model": "sat.estado", "pk": 74, "fields": {"clave": "TN", "pais": "USA", "descripcion": "Tennessee"}}, {"model": "sat.estado", "pk": 75, "fields": {"clave": "TX", "pais": "USA", "descripcion": "Texas"}}, {"model": "sat.estado", "pk": 76, "fields": {"clave": "UT", "pais": "USA", "descripcion": "Utah"}}, {"model": "sat.estado", "pk": 77, "fields": {"clave": "VT", "pais": "USA", "descripcion": "Vermont"}}, {"model": "sat.estado", "pk": 78, "fields": {"clave": "VA", "pais": "USA", "descripcion": "Virginia"}}, {"model": "sat.estado", "pk": 79, "fields": {"clave": "WV", "pais": "USA", "descripcion": "Virginia Occidental"}}, {"model": "sat.estado", "pk": 80, "fields": {"clave": "WA", "pais": "USA", "descripcion": "Washington"}}, {"model": "sat.estado", "pk": 81, "fields": {"clave": "WI", "pais": "USA", "descripcion": "Wisconsin"}}, {"model": "sat.estado", "pk": 82, "fields": {"clave": "WY", "pais": "USA", "descripcion": "Wyoming"}}, {"model": "sat.estado", "pk": 83, "fields": {"clave": "ON", "pais": "CAN", "descripcion": "Ontario\u00a0"}}, {"model": "sat.estado", "pk": 84, "fields": {"clave": "QC", "pais": "CAN", "descripcion": "\u00a0Quebec\u00a0"}}, {"model": "sat.estado", "pk": 85, "fields": {"clave": "NS", "pais": "CAN", "descripcion": "\u00a0Nueva Escocia"}}, {"model": "sat.estado", "pk": 86, "fields": {"clave": "NB", "pais": "CAN", "descripcion": "Nuevo Brunswick\u00a0"}}, {"model": "sat.estado", "pk": 87, "fields": {"clave": "MB", "pais": "CAN", "descripcion": "\u00a0Manitoba"}}, {"model": "sat.estado", "pk": 88, "fields": {"clave": "BC", "pais": "CAN", "descripcion": "\u00a0Columbia Brit\u00e1nica"}}, {"model": "sat.estado", "pk": 89, "fields": {"clave": "PE", "pais": "CAN", "descripcion": "\u00a0Isla del Pr\u00edncipe Eduardo"}}, {"model": "sat.estado", "pk": 90, "fields": {"clave": "SK", "pais": "CAN", "descripcion": "\u00a0Saskatchewan"}}, {"model": "sat.estado", "pk": 91, "fields": {"clave": "AB", "pais": "CAN", "descripcion": "\u00a0Alberta"}}, {"model": "sat.estado", "pk": 92, "fields": {"clave": "NL", "pais": "CAN", "descripcion": "\u00a0Terranova y Labrador"}}, {"model": "sat.estado", "pk": 93, "fields": {"clave": "NT", "pais": "CAN", "descripcion": "\u00a0Territorios del Noroeste"}}, {"model": "sat.estado", "pk": 94, "fields": {"clave": "YT", "pais": "CAN", "descripcion": "\u00a0Yuk\u00f3n"}}, {"model": "sat.estado", "pk": 95, "fields": {"clave": "UN", "pais": "CAN", "descripcion": "\u00a0Nunavut"}}]